file_organizer/__init__.py
file_organizer/cli.py
file_organizer/organizer.py
file_organizer/undo.py
SmartFileOrganizer-0.0.1.dist-info/LICENSE.txt
SmartFileOrganizer-0.0.1.dist-info/METADATA
SmartFileOrganizer-0.0.1.dist-info/WHEEL
SmartFileOrganizer-0.0.1.dist-info/entry_points.txt
SmartFileOrganizer-0.0.1.dist-info/top_level.txt
SmartFileOrganizer-0.0.1.dist-info/RECORD
